{
  "correction_id": "owner_correction_batch_029_celebrity_clip_opinion",
  "applies_to_sources": [288, 289, 290],
  "status": "stored_not_runtime_verified",
  "owner_intent": {
    "summary": "동일 연예인의 예능 프로그램 장면과 개인 영상 캡처를 연속해서 사용하고, 그 위에 가벼운 개인 의견과 사적인 맥락 및 짤 반응을 더할 수 있음을 보여주는 사례다.",
    "not_only": "발언-상황설정-반전행동이라는 서사 구조만을 학습하는 사례가 아니다."
  },
  "standing_learning_rules": [
    "뉴스 계정이 아닌 연예, 썰, 관계, 도파민 성격의 계정에는 뉴스 보도용 이미지 기준을 일률적으로 적용하지 않고 더 유연하게 운영한다.",
    "연예인 콘텐츠는 실제 관련성이 있는 예능 장면, 본인 채널 또는 개인 영상의 서로 다른 캡처를 같은 주제 안에서 이어 사용할 수 있다.",
    "해당 인물과 화제가 실제로 연결되어 있다면 연예인 이미지, 방송 장면, 공개된 개인 영상 캡처를 적정 수준에서 활용할 수 있다.",
    "출처 장면의 의미를 왜곡하지 않는 범위에서 제작자의 짧은 개인 의견, 공감, 놀림, 반응 문구를 섞을 수 있다.",
    "공개된 영상에서 드러난 가벼운 일상이나 사적인 면모는 과도한 침해나 단정 없이 콘텐츠의 친근한 맥락으로 활용할 수 있다.",
    "짤과 반응형 문구는 사실 전달을 대체하는 증거가 아니라 분위기, 공감, 재미를 강화하는 편집 요소로 사용한다.",
    "서로 다른 캡처라도 동일 인물과 동일 화제의 맥락이 분명해야 하며, 무관한 연예인 이미지를 분위기용으로 붙이지 않는다."
  ],
  "production_pattern": {
    "possible_sequence": [
      "예능 프로그램의 발언 또는 표정 장면",
      "동일 연예인의 개인 영상이나 본인 채널 속 일상 장면",
      "또 다른 관련 장면과 제작자의 짧은 의견 또는 짤 반응"
    ],
    "tone": "뉴스 계정이 아니라면 가볍고 친근하며 약간 사적인 느낌까지 유연하게 허용하되, 악의적 추측이나 확인되지 않은 사생활 단정은 피한다."
  },
  "runtime_connection": false,
  "tested": false
}
