{
  "schema_version": "1.0",
  "batch_id": "owner_source_241_250",
  "source_range": [
    241,
    250
  ],
  "status": "stored_not_runtime_verified",
  "installation_performed": false,
  "runtime_connected": false,
  "performance_verified": false,
  "items": [
    {
      "source_id": 241,
      "source_type": "sequential_outdoor_ad_reference",
      "content_analysis": [
        "선사유적공원까지 남은 거리가 200m, 130m, 100m, 50m, 10m로 줄어들수록 원시인이 더 많이 모습을 드러내고 환영하는 옥외 광고다.",
        "목적지 접근이라는 실제 이동 흐름을 이야기 진행으로 바꿔 방문 기대감을 만든다."
      ],
      "design_analysis": [
        "같은 흰색 세로 표지판, 동일 인물, 거리 숫자를 반복하고 거리 변화에 따라 인물의 노출과 손동작만 점진적으로 바꾼다.",
        "여러 광고판을 순서대로 지나쳐야 완성되는 현실 공간형 캐러셀이다.",
        "문장이 거의 없어도 반복, 변화, 목적지 정보만으로 메시지가 이해된다."
      ],
      "project_use": [
        "카드뉴스에서 같은 배경과 인물을 유지하고 슬라이드마다 거리, 시간, 감정 또는 행동을 조금씩 변화시키는 진행 구조로 활용할 수 있다.",
        "여행, 행사, 출시 예고, 카운트다운처럼 가까워지는 경험을 다루는 콘텐츠에 적합하다."
      ],
      "learning_rule": "순차형 콘텐츠는 매 장면을 새로 만들기보다 고정 요소와 변화 요소를 분리하고 변화 폭을 누적해 다음 장면을 기대하게 한다.",
      "uncertainty": [
        "실제 캠페인 제작 주체와 효과 수치는 이미지에서 검증되지 않았다."
      ]
    },
    {
      "source_id": 242,
      "source_type": "object_world_visual_metaphor",
      "content_analysis": [
        "비행기 모형의 표면을 주변 지도와 동일하게 만들어 비행기가 지도 속 경로에 섞인 것처럼 보이게 한다.",
        "이동 수단과 이동 정보를 하나의 물성으로 결합한 시각 아이디어다."
      ],
      "design_analysis": [
        "저채도 지도와 동일한 패턴을 비행기 전체에 입혀 배경과 피사체의 경계를 흐린다.",
        "중앙 피사체와 넓은 여백, 짧은 제목만으로 첫 화면의 발견감을 만든다."
      ],
      "project_use": [
        "여행, 배송, 이동 경로, 위치 기반 서비스에서 대상과 지도 또는 환경을 같은 패턴으로 연결하는 이미지 프롬프트 참고가 된다."
      ],
      "learning_rule": "대상을 배경과 위장시키는 표현은 단순 색상 일치보다 기능적으로 연결된 패턴과 경로를 사용해야 메시지가 생긴다.",
      "uncertainty": [
        "이미지의 생성 방식과 실제 캠페인 여부는 확인되지 않았다."
      ]
    },
    {
      "source_id": 243,
      "source_type": "privacy_concept_ad_reference",
      "content_analysis": [
        "초상화 속 얼굴이 길게 왜곡되어 얼굴 인식에 실패한 장면과 Apple의 개인정보 보호 문구를 결합한다.",
        "기술 기능을 설명하지 않고 인식 불가능한 얼굴이라는 시각적 결과로 프라이버시 메시지를 전달한다."
      ],
      "design_analysis": [
        "고전 유화의 어두운 질감과 현대적인 시스템 알림창을 충돌시켜 시간대와 매체의 대비를 만든다.",
        "얼굴 왜곡, Face Not Recognized 알림, 짧은 브랜드 문구가 순서대로 읽힌다."
      ],
      "project_use": [
        "AI, 보안, 개인정보처럼 추상적인 기술 주제에서 실패 화면이나 시스템 UI를 시각 은유로 사용하는 참고가 된다."
      ],
      "learning_rule": "기술 메시지는 실제 인터페이스 문법과 한 번에 이해되는 시각적 결과를 결합하면 긴 설명 없이 전달할 수 있다.",
      "uncertainty": [
        "공식 Apple 광고인지 팬 제작 또는 생성 이미지인지 확인되지 않았으므로 브랜드 사례로 단정하지 않는다.",
        "타사 상표와 UI를 실제 제작물에 그대로 사용하지 않는다."
      ]
    },
    {
      "source_id": 244,
      "source_type": "product_structure_human_metaphor",
      "content_analysis": [
        "CPU의 촘촘한 금속 핀 위에 같은 재질의 작은 사람이 누운 모습을 결합해 내부 부품을 침대나 지압판처럼 보이게 한다.",
        "제품 구조의 반복 패턴을 인간 행동이 가능한 공간으로 재해석한다."
      ],
      "design_analysis": [
        "검정과 금색의 제한된 색상, 중앙 인물, 규칙적인 핀 배열이 고급스럽고 정밀한 인상을 만든다.",
        "인물이 제품과 같은 재질과 패턴을 가져 이질적인 합성보다 한 세계 안의 조형물처럼 보인다."
      ],
      "project_use": [
        "전자제품, 구조, 성분, 소재를 설명할 때 제품의 미세 구조를 거대한 환경으로 확대하고 작은 인물을 배치하는 프롬프트 레퍼런스로 활용할 수 있다."
      ],
      "learning_rule": "제품 의인화는 임의의 사람을 얹는 것이 아니라 제품의 재질, 반복 구조, 기능과 맞는 자세와 행동을 설계한다.",
      "uncertainty": [
        "공식 Intel 광고와 실제 생성 방식은 확인되지 않았다."
      ]
    },
    {
      "source_id": 245,
      "source_type": "product_fit_personification",
      "content_analysis": [
        "작은 노란 인물이 탁상등 기둥 뒤에 밀착한 모습을 통해 어디에나 잘 맞는다는 메시지를 표현한다.",
        "제품 색상과 동일한 캐릭터를 사용해 인물을 장식이 아니라 제품의 일부처럼 만든다."
      ],
      "design_analysis": [
        "아이보리 배경에 노란 제품 하나를 크게 배치하고 검정 문구와 가격만 남긴 미니멀한 상품 광고 구성이다.",
        "작은 인물을 발견하는 순간 평범한 제품 사진이 이야기 장면으로 바뀐다."
      ],
      "commerce_use": [
        "공간 절약, 밀착, 휴대성, 호환성 같은 상품 기능을 작은 캐릭터의 자세로 시각화하는 방법에 활용할 수 있다."
      ],
      "learning_rule": "상품 기능을 캐릭터로 설명할 때 인물의 크기, 색, 위치와 자세가 기능 자체를 보여주도록 한다.",
      "uncertainty": [
        "표시 가격과 캠페인 진위는 현재 상품 정보로 사용할 수 없다."
      ]
    },
    {
      "source_id": 246,
      "source_type": "packaging_action_metaphor",
      "content_analysis": [
        "케첩 용기에서 나온 케첩을 작은 사람이 몸을 비틀어 짜내는 모습으로 만들어 제품 사용 행동을 의인화한다.",
        "포장 구조와 내용물의 점성을 하나의 동작으로 표현한다."
      ],
      "design_analysis": [
        "흰 배경, 뒤집힌 제품, 붉은 내용물 캐릭터, 큰 브랜드 문구만 사용해 메시지가 즉시 보인다.",
        "내용물 자체가 인물이 되어 색상과 재질의 연결이 자연스럽다."
      ],
      "commerce_use": [
        "제형, 탄성, 압축, 분사, 흡수처럼 상품을 사용할 때 나타나는 물리적 행동을 캐릭터 포즈로 전환하는 참고가 된다."
      ],
      "learning_rule": "제품 의인화는 포장, 내용물, 사용 동작 중 하나의 핵심 물성을 선택해 캐릭터 행동으로 번역한다.",
      "uncertainty": [
        "공식 Heinz 광고인지와 생성 여부는 확인되지 않았으며 그대로 복제하지 않는다."
      ]
    },
    {
      "source_id": 247,
      "source_type": "trend_curation_cover",
      "content_analysis": [
        "회사에서 몰래 멧챠 카멜레온을 하는 법이라는 POV 훅과 함께 빠르게 활용할 트렌드 사례 네 가지를 소개하는 첫 장이다.",
        "사무실 실사 위 모자와 작은 사람 모양 오브제를 결합해 트렌드 자체를 즉시 시연한다."
      ],
      "design_analysis": [
        "검정 반투명 제목 박스, 형광 초록 강조색, PICK 번호, 큰 흰색 제목을 사용한 트렌드 큐레이션형 표지다.",
        "실제 사무실 장면과 장난스러운 오브제가 호기심을 만들지만 글자 요소가 많아 시선이 분산될 수 있다."
      ],
      "project_use": [
        "트렌드 소개 콘텐츠는 설명만 하지 않고 첫 화면에서 실제 적용 장면을 먼저 보여주는 방식으로 활용할 수 있다."
      ],
      "learning_rule": "트렌드 콘텐츠의 첫 장은 이름보다 사용 장면과 재미를 먼저 보여주고, 계정 목적에 맞는 이유를 뒤에서 설명한다.",
      "uncertainty": [
        "트렌드의 지속 기간과 확산 규모는 이 이미지로 확인되지 않았다."
      ]
    },
    {
      "source_id": 248,
      "source_type": "paper_squishy_brand_trend_explanation",
      "content_analysis": [
        "CLIO가 자사 제품을 종이 스퀴시로 만드는 영상을 올린 뒤 여러 뷰티 브랜드가 각자 제품을 같은 형식으로 제작하고 댓글로 교류한 사례를 설명한다.",
        "하나의 저비용 제작 놀이가 브랜드 간 참여와 대화로 확산되는 구조다."
      ],
      "design_analysis": [
        "연한 녹색 문서형 카드에 원 게시물 이미지 두 개, 댓글 캡처, 번호 제목, 형광 밑줄을 배치한다.",
        "근거 화면과 해설을 함께 보여줘 단순 주장보다 사례 이해가 쉽지만 본문이 길다."
      ],
      "commerce_use": [
        "뷰티나 패션 상품의 패키지를 종이, 점토, 미니어처, 음식 등 다른 촉감 매체로 재현해 친근한 참여형 콘텐츠를 만들 수 있다.",
        "상품을 직접 판매하기보다 브랜드 성격과 패키지 인지도를 놀이로 확산시키는 상단 퍼널 콘텐츠에 적합하다."
      ],
      "learning_rule": "브랜드 트렌드 참여는 형식을 복제하는 데서 끝내지 않고 자사 제품의 형태, 색, 패키지 특징과 댓글 상호작용까지 연결한다.",
      "uncertainty": [
        "화제성과 참여 효과는 게시물 설명이며 실제 캠페인 성과는 검증되지 않았다."
      ]
    },
    {
      "source_id": 249,
      "source_type": "cross_brand_social_participation_evidence",
      "content_analysis": [
        "Wonderbath와 CLIO 등 여러 브랜드가 종이 스퀴시 콘텐츠를 만들고 인용, 댓글, 태그로 서로 참여한 실제 화면을 모은 사례다.",
        "한 브랜드의 포맷이 다른 브랜드의 제품으로 변주되고 원 브랜드가 다시 반응하면서 연쇄 대화가 생긴다."
      ],
      "design_analysis": [
        "SNS 게시물 캡처를 콜라주처럼 배치하고 형광 녹색 라벨로 공통 현상을 표시한다.",
        "완성 이미지보다 실제 참여 흔적과 계정 관계가 핵심 증거로 사용된다."
      ],
      "commerce_use": [
        "경쟁 또는 인접 브랜드가 참여할 수 있는 열린 형식과 가벼운 댓글 문법을 설계하는 참고가 된다.",
        "소비자도 같은 재료로 따라 만들 수 있으면 UGC 확장 가능성이 생긴다."
      ],
      "learning_rule": "트렌드 확산 여부는 원본 조회 수만 보지 않고 재제작 계정, 인용, 댓글 대화, 제품별 변주와 소비자 참여를 함께 관찰한다.",
      "uncertainty": [
        "캡처된 수치와 게시물은 특정 시점의 자료이며 현재 상태나 전체 확산 규모를 의미하지 않는다."
      ]
    },
    {
      "source_id": 250,
      "source_type": "camouflage_object_trend_example",
      "content_analysis": [
        "회색 셔츠 위에 같은 계열 색의 작은 사람 오브제를 붙여 배경에 섞이는 멧챠 카멜레온 놀이를 사무실 장면에 적용한다.",
        "일상 사물의 색과 표면에 캐릭터를 위장시키고 발견하는 재미를 만든다."
      ],
      "design_analysis": [
        "세로 실사 영상, 검정 POV 제목 박스, 형광 녹색 설명 라벨을 사용한다.",
        "작은 오브제를 찾는 관찰 행동 자체가 시청 지속을 유도하는 장치다."
      ],
      "project_use": [
        "패션 색상, 소재 매칭, 숨은 상품 찾기, 사무실 또는 일상 장면의 발견형 숏폼에 응용할 수 있다.",
        "계정에 맞지 않는 밈을 그대로 따라 하기보다 상품 색상이나 주제 기능과 자연스럽게 연결해야 한다."
      ],
      "learning_rule": "위장형 트렌드는 배경과 캐릭터의 색, 질감, 방향을 맞추고 발견까지의 시간을 짧게 설계해 참여 재미를 만든다.",
      "uncertainty": [
        "오브제의 명칭, 유래, 현재 유행성은 별도 검증이 필요하다."
      ]
    }
  ],
  "cross_item_learning": [
    "같은 인물이나 사물을 반복하면서 거리, 자세, 노출 정도만 변화시키면 현실 공간과 캐러셀 모두에서 순차 서사를 만들 수 있다.",
    "초현실 상품 이미지는 제품과 무관한 인물을 붙이는 것이 아니라 재질, 구조, 내용물, 기능, 사용 동작 중 하나를 사람의 행동으로 번역해야 한다.",
    "대상을 배경에 위장시키거나 작은 캐릭터를 숨기면 발견 행동이 훅이 되지만 메시지와 상품 관계가 없으면 일회성 장식에 그친다.",
    "트렌드 참여는 빠른 복제보다 계정과 제품에 맞는 변주, 실제 댓글 대화, 다른 계정의 재제작까지 포함해야 확산 구조가 생긴다.",
    "종이 스퀴시처럼 저비용 촉감 놀이도 패키지 인지도, 브랜드 성격, UGC와 브랜드 간 대화를 연결하는 콘텐츠가 될 수 있다.",
    "브랜드 로고와 캠페인 이미지는 학습 레퍼런스로만 사용하며 공식 광고 여부가 불명확한 이미지를 실제 사실이나 원본 자산으로 취급하지 않는다.",
    "전체 자료 분석 전에는 이전 광고 발상, 밈, 이미지 프롬프트 자료와 최종 통합하지 않는다."
  ],
  "deferred_cross_batch_work": {
    "status": "deferred_until_full_corpus_review",
    "items": [
      "초현실 광고 사례를 위장, 미니어처, 의인화, 공간 순차, 재질 변환 유형으로 분류한다.",
      "멧챠 카멜레온과 종이 스퀴시의 실제 유래, 확산 기간, 플랫폼별 반응을 추후 비교한다.",
      "뷰티·패션 계정에서 활용 가능한 저비용 참여형 포맷과 상품 근거 연결 방식을 정리한다."
    ]
  },
  "project_boundary": {
    "knowledge_stored": true,
    "runtime_connected": false,
    "tested": false,
    "trend_verified_current": false,
    "tool_installed": false,
    "content_generated": false,
    "external_write_performed": false
  }
}
