{
  "topic": "AI content automation",
  "summary": "AI content automation refers to the use of artificial intelligence technologies to create, manage, and optimize digital content with minimal human intervention, enhancing efficiency and consistency in content production.",
  "key_points": [
    "AI tools can generate written, visual, and audio content based on given inputs or data patterns.",
    "Automation helps streamline repetitive tasks like content scheduling, personalization, and distribution.",
    "It enables faster content production and can support large-scale content strategies while maintaining quality."
  ],
  "audience_interest": [
    "개인과 기업 모두 시간과 비용을 절약할 수 있는 방법에 대한 관심",
    "콘텐츠 마케팅과 디지털 미디어 분야에서 효율성을 높이는 최신 기술에 대한 이해"
  ],
  "content_angle": "AI가 콘텐츠 제작 과정을 어떻게 변화시키고, 실무에서 활용할 수 있는 구체적인 사례와 장점을 중심으로 설명",
  "status": "research_completed"
}